cherry/__init__.py
cherry/api.py
cherry/base.py
cherry/classifyer.py
cherry/common.py
cherry/displayer.py
cherry/exceptions.py
cherry/performancer.py
cherry/searcher.py
cherry/trainer.py
cherry-3.0.dist-info/LICENSE.txt
cherry-3.0.dist-info/METADATA
cherry-3.0.dist-info/WHEEL
cherry-3.0.dist-info/top_level.txt
cherry-3.0.dist-info/RECORD
